auscopecat/__init__.py
auscopecat/analytics.py
auscopecat/api.py
auscopecat/auscopecat_types.py
auscopecat/network.py
auscopecat/nvcl.py
auscopecat/utils.py
auscopecat-1.0.2.dist-info/METADATA
auscopecat-1.0.2.dist-info/WHEEL
auscopecat-1.0.2.dist-info/top_level.txt
auscopecat-1.0.2.dist-info/RECORD
