Metadata-Version: 2.4
Name: auscopecat
Version: 1.0.2
Summary: Access to AuScope's catalogue of geoscience datasets from sources all over Australia
Author-email: AuScope MAINTAIN <cg-admin@csiro.au>
Project-URL: Repository, https://github.com/AuScope/AuScope-Cat
Classifier: Development Status :: 4 - Beta
Classifier: Intended Audience :: Science/Research
Classifier: License :: OSI Approved :: GNU Lesser General Public License v2 (LGPLv2)
Classifier: Operating System :: POSIX :: Linux
Classifier: Programming Language :: Python :: 3.10
Classifier: Programming Language :: Python :: 3.11
Classifier: Programming Language :: Python :: 3.12
Classifier: Programming Language :: Python :: 3.13
Classifier: Topic :: Scientific/Engineering
Requires-Python: >=3.10
Requires-Dist: requests
Requires-Dist: numpy
Requires-Dist: pandas
